peegeem/__init__.py
peegeem/datasets.py
peegeem-0.0.2.dist-info/METADATA
peegeem-0.0.2.dist-info/WHEEL
peegeem-0.0.2.dist-info/licenses/LICENSE
peegeem-0.0.2.dist-info/RECORD
