Metadata-Version: 2.4
Name: peegeem
Version: 0.0.2
Summary: PGMs that are fun to play with
Author: Vincent
License-Expression: MIT
License-File: LICENSE
Requires-Python: >=3.8
Requires-Dist: numpy>2
Requires-Dist: pandas
Requires-Dist: pgmpy
Provides-Extra: dev
Requires-Dist: marimo; extra == 'dev'
Requires-Dist: pytest>=7.0; extra == 'dev'
Requires-Dist: wigglystuff; extra == 'dev'
